README.md
setup.py
django_logstash_logger/__init__.py
django_logstash_logger/_compat.py
django_logstash_logger/formatters.py
django_logstash_logger/handlers.py
django_logstash_logger.egg-info/PKG-INFO
django_logstash_logger.egg-info/SOURCES.txt
django_logstash_logger.egg-info/dependency_links.txt
django_logstash_logger.egg-info/requires.txt
django_logstash_logger.egg-info/top_level.txt