Metadata-Version: 1.1
Name: django-logstash-logger
Version: 0.0.1
Summary: Simple logstash-compatible log handler for Django-based projects
Home-page: https://github.com/astrikov-d/django-logstash-logger
Author: Dmitry Astrikov
Author-email: astrikov.d@gmail.com
License: Apache License 2.0
Platform: UNKNOWN
Classifier: Development Status :: 4 - Beta
Classifier: Environment :: Console
Classifier: Intended Audience :: Developers
Classifier: Operating System :: OS Independent
Classifier: Programming Language :: Python
Classifier: Programming Language :: Python :: 2.7
Classifier: Programming Language :: Python :: 3.4
Classifier: Programming Language :: Python :: Implementation :: CPython
Classifier: Programming Language :: Python :: Implementation :: PyPy
